osvolbackup/__init__.py
osvolbackup/__main__.py
osvolbackup/backup.py
osvolbackup/osauth.py
osvolbackup/server.py
osvolbackup/verbose.py
osvolbackup/cli/__init__.py
osvolbackup/cli/server.py
osvolbackup-0.0.2.dist-info/LICENSE
osvolbackup-0.0.2.dist-info/METADATA
osvolbackup-0.0.2.dist-info/WHEEL
osvolbackup-0.0.2.dist-info/entry_points.txt
osvolbackup-0.0.2.dist-info/top_level.txt
osvolbackup-0.0.2.dist-info/RECORD
